[
	{
		"_id": "5d725a4a7b292f5f8ceff789",
		"name": "hamid achouri",
		"description": "something about the delivery",
		"distance": 23,
		"minimumSkill": "beginner",
		"restaurateur": "5d713995b721c3bb38c1f5d0",
		"user": "5d7a514b5d2c12c7449be045"
	},
	{
		"_id": "5d725a4a7b292f5f8ceff789",
		"title": "Pizza to bouloughine",
		"description": "something about the delivery",
		"distance": 20,
		"restaurateur": "5d713995b721c3bb38c1f5d0",
		"user": "5d7a514b5d2c12c7449be046"
	},
	{
		"_id": "5d725a4a7b292f5f8ceff789",
		"title": "Pizza to boumerdas",
		"description": "something about the delivery",
		"distance": 24,
		"restaurateur": "5d713995b721c3bb38c1f5d0",
		"user": "5d7a514b5d2c12c7449be047"
	},
	{
		"_id": "5d725a4a7b292f5f8ceff789",
		"title": "Pizza to bousma3il",
		"description": "something about the delivery",
		"distance": 40,
		"restaurateur": "5d713995b721c3bb38c1f5d0",
		"user": "5d7a514b5d2c12c7449be048"
	},
	{
		"_id": "5d725a4a7b292f5f8ceff789",
		"title": "Pizza to bouharoun",
		"description": "something about the delivery",
		"distance": 6,
		"restaurateur": "5d713995b721c3bb38c1f5d0",
		"user": "5d7a514b5d2c12c7449be049"
	}
	
]
